yatools/__init__.py
yatools/logging_config.py
yatools-0.0.2.dist-info/METADATA
yatools-0.0.2.dist-info/WHEEL
yatools-0.0.2.dist-info/licenses/LICENCE
yatools-0.0.2.dist-info/RECORD
