Metadata-Version: 2.3
Name: yatools
Version: 0.0.2
Summary: Logging tools for python
Project-URL: Homepage, https://github.com/EmixD/yatools
Project-URL: Bug Tracker, https://github.com/EmixD/yatools/issues
Author-email: "Ivan I. Yakovkin" <yakovkinii@gmail.com>
License-File: LICENCE
Classifier: License :: OSI Approved :: MIT License
Classifier: Operating System :: OS Independent
Classifier: Programming Language :: Python :: 3
Requires-Python: >=3.7
Requires-Dist: coloredlogs
